repobee_junit4/__init__.py
repobee_junit4/__version.py
repobee_junit4/_exception.py
repobee_junit4/_generate_rtd.py
repobee_junit4/_java.py
repobee_junit4/_junit4_runner.py
repobee_junit4/_output.py
repobee_junit4/junit4.py
repobee_junit4-2.0.0.dist-info/LICENSE
repobee_junit4-2.0.0.dist-info/METADATA
repobee_junit4-2.0.0.dist-info/WHEEL
repobee_junit4-2.0.0.dist-info/top_level.txt
repobee_junit4-2.0.0.dist-info/RECORD
