Metadata-Version: 2.1
Name: repobee-junit4
Version: 2.0.0
Summary: JUnit4 runner plugin for RepoBee
Home-page: https://github.com/repobee/repobee-junit4
Author: Simon Larsén
Author-email: slarse@kth.se
License: MIT
Download-URL: https://github.com/repobee/repobee-junit4/archive/v2.0.0.tar.gz
Platform: UNKNOWN
Classifier: Development Status :: 3 - Alpha
Classifier: Intended Audience :: Education
Classifier: Programming Language :: Python :: 3.9
Classifier: Programming Language :: Python :: 3.10
Classifier: Programming Language :: Python :: 3.11
Classifier: Programming Language :: Python :: Implementation :: CPython
Classifier: License :: OSI Approved :: MIT License
Classifier: Operating System :: POSIX
Requires-Python: >=3.9
License-File: LICENSE
Requires-Dist: repobee >=3.4.1
Requires-Dist: daiquiri
Requires-Dist: colored >=2.0.0
Provides-Extra: test
Requires-Dist: appdirs ; extra == 'test'
Requires-Dist: bandit ; extra == 'test'
Requires-Dist: black ; extra == 'test'
Requires-Dist: codecov ; extra == 'test'
Requires-Dist: daiquiri ; extra == 'test'
Requires-Dist: flake8 ; extra == 'test'
Requires-Dist: pylint ; extra == 'test'
Requires-Dist: pytest-cov >=2.5.1 ; extra == 'test'
Requires-Dist: pytest-mock ; extra == 'test'
Requires-Dist: pytest >=4.0.0 ; extra == 'test'
